autoinit/__init__.py
autoinit/core.py
autogen_init-2.0.4.dist-info/LICENSE
autogen_init-2.0.4.dist-info/METADATA
autogen_init-2.0.4.dist-info/WHEEL
autogen_init-2.0.4.dist-info/top_level.txt
autogen_init-2.0.4.dist-info/RECORD
