Metadata-Version: 2.1
Name: autogen-init
Version: 2.0.4
Summary: A Python package that updates init.py files across a package for direct imports.
Home-page: https://github.com/dsdanielpark/auto-init
Author: Daniel Park
Author-email: parkminwoo1991@gmail.com
Keywords: Python,Python package init,package init,autoinit,package initialization,init.py automation
Classifier: Development Status :: 2 - Pre-Alpha
Classifier: Intended Audience :: Developers
Classifier: Natural Language :: English
Classifier: Programming Language :: Python :: 3
Classifier: License :: OSI Approved :: MIT License
Classifier: Topic :: Software Development :: Libraries :: Python Modules
Requires-Python: >=3.6
License-File: LICENSE
